cli/__init__.py
cli/pcct/__init__.py
cli/pcct/__main__.py
cli/pcct/benchmark_cli.py
cli/pcct/breakdown_cli.py
cli/pcct/build_cli.py
cli/pcct/doctor.py
cli/pcct/execution.py
cli/pcct/help_panels.py
cli/pcct/main.py
cli/pcct/option_defs.py
cli/pcct/options.py
cli/pcct/plugins_cli.py
cli/pcct/profile.py
cli/pcct/query.py
cli/pcct/query_cli.py
cli/pcct/runtime_config.py
cli/pcct/support/baseline_utils.py
cli/pcct/support/benchmark_utils.py
cli/pcct/support/gate_utils.py
cli/pcct/support/runtime_utils.py
cli/pcct/support/telemetry_utils.py
cli/pcct/telemetry_cli.py
covertreex-0.4.5.dist-info/METADATA
covertreex-0.4.5.dist-info/WHEEL
covertreex-0.4.5.dist-info/licenses/LICENSE
covertreex/__init__.py
covertreex/__main__.py
covertreex/algo/__init__.py
covertreex/algo/_grid_numba.py
covertreex/algo/_mis_numba.py
covertreex/algo/_residual_scope_numba.py
covertreex/algo/_scope_numba.py
covertreex/algo/_traverse_numba.py
covertreex/algo/_traverse_sparse_numba.py
covertreex/algo/batch/__init__.py
covertreex/algo/batch/insert.py
covertreex/algo/batch/types.py
covertreex/algo/batch_delete.py
covertreex/algo/batch_insert.py
covertreex/algo/batch_order.py
covertreex/algo/conflict/__init__.py
covertreex/algo/conflict/arena.py
covertreex/algo/conflict/base.py
covertreex/algo/conflict/builders.py
covertreex/algo/conflict/runner.py
covertreex/algo/conflict/strategies.py
covertreex/algo/mis.py
covertreex/algo/order/__init__.py
covertreex/algo/order/helpers.py
covertreex/algo/order/strategy.py
covertreex/algo/semisort.py
covertreex/algo/traverse/__init__.py
covertreex/algo/traverse/_residual_parent_numba.py
covertreex/algo/traverse/base.py
covertreex/algo/traverse/runner.py
covertreex/algo/traverse/strategies/__init__.py
covertreex/algo/traverse/strategies/common.py
covertreex/algo/traverse/strategies/euclidean.py
covertreex/algo/traverse/strategies/registry.py
covertreex/algo/traverse/strategies/residual.py
covertreex/api/__init__.py
covertreex/api/factory.py
covertreex/api/pcct.py
covertreex/api/runtime.py
covertreex/baseline.py
covertreex/config.py
covertreex/core/__init__.py
covertreex-0.4.5.dist-info/RECORD
