Metadata-Version: 2.4
Name: covertreex
Version: 0.4.5
Requires-Dist: numpy>=2.0.0
Requires-Dist: typing-extensions>=4.9.0
Requires-Dist: typer>=0.12.5
Requires-Dist: pydantic>=2.7
Requires-Dist: pyyaml>=6.0
Requires-Dist: jax>=0.4.28 ; extra == 'jax'
Requires-Dist: jaxlib>=0.4.28 ; extra == 'jax'
Requires-Dist: numba>=0.59.0 ; extra == 'numba'
Requires-Dist: pytest>=8.2 ; extra == 'dev'
Requires-Dist: pytest-benchmark>=4.0.0 ; extra == 'dev'
Requires-Dist: pytest-chronicle>=0.3.1 ; extra == 'dev'
Requires-Dist: rich>=13.7 ; extra == 'dev'
Requires-Dist: hypothesis>=6.100 ; extra == 'dev'
Requires-Dist: ruff>=0.6.4 ; extra == 'dev'
Requires-Dist: mypy>=1.11 ; extra == 'dev'
Requires-Dist: pre-commit>=3.8 ; extra == 'dev'
Requires-Dist: psutil>=5.9 ; extra == 'dev'
Requires-Dist: twine>=5.0 ; extra == 'dev'
Requires-Dist: build>=1.0 ; extra == 'dev'
Requires-Dist: covertree>=1.0.0 ; extra == 'baseline'
Requires-Dist: scipy>=1.11 ; extra == 'baseline'
Requires-Dist: mlpack>=4.6 ; extra == 'baseline'
Requires-Dist: scikit-learn>=1.4 ; extra == 'baseline'
Requires-Dist: matplotlib>=3.8 ; extra == 'viz'
Provides-Extra: jax
Provides-Extra: numba
Provides-Extra: dev
Provides-Extra: baseline
Provides-Extra: viz
License-File: LICENSE
Summary: Parallel compressed cover tree (PCCT) library targeting JAX-based Vecchia GP workloads.
Author-email: Liam <liam@example.com>
License: Apache-2.0
Requires-Python: >=3.12
Project-URL: homepage, https://github.com/chiark/cover-tree
Project-URL: repository, https://github.com/chiark/cover-tree
